octutilsprod/__init__.py
octutilsprod/functions.py
octutilsprod-0.3.4.dist-info/licenses/License.txt
octutilsprod-0.3.4.dist-info/METADATA
octutilsprod-0.3.4.dist-info/WHEEL
octutilsprod-0.3.4.dist-info/top_level.txt
octutilsprod-0.3.4.dist-info/RECORD
