Metadata-Version: 2.4
Name: octutilsprod
Version: 0.3.4
Summary: Extracting the metadata & source lineage items used in the Semantic Models in Microsoft Fabric
Author-email: Vamshi Krishna <vamshikrishna.r@sonata-software.com>
License-Expression: MIT
Classifier: Programming Language :: Python :: 3
Classifier: Operating System :: OS Independent
Requires-Python: >=3.11
License-File: License.txt
Dynamic: license-file
